pohlednice/#__init__.py#
pohlednice/__init__.py
pohlednice/__init__.py~
pohlednice-0.2.1.dist-info/METADATA
pohlednice-0.2.1.dist-info/WHEEL
pohlednice-0.2.1.dist-info/RECORD
