Metadata-Version: 2.1
Name: pohlednice
Version: 0.2.1
Summary: Pythonic implementation of the 'postcard' wire format
Author: Charles Bajeux
Author-email: charles.bajeux@gmail.com
Requires-Python: >=3.12,<4.0
Classifier: Programming Language :: Python :: 3
Classifier: Programming Language :: Python :: 3.12
